README.rst
setup.py
pyipa/IPAparser.py
pyipa/__init__.py
pyipa/bplist.py
pyipa/main.py
pyipa.egg-info/PKG-INFO
pyipa.egg-info/SOURCES.txt
pyipa.egg-info/dependency_links.txt
pyipa.egg-info/entry_points.txt
pyipa.egg-info/requires.txt
pyipa.egg-info/top_level.txt