Metadata-Version: 1.0
Name: pyipa
Version: 1.2.0
Summary: Python module to extract useful info from an IPA
Home-page: https://github.com/mogui
Author: Niko Usai
Author-email: mogui83@gmail.com
License: ISC
Platform: UNKNOWN
